{
  "totalProduct": "8",

  "product": [
    {
      "image":"nokia-7-plus-.jpg",
      "name": "galaxy j1",
      "price": "23k",
      "camera": "25mp",
      "company": "samsung",
      "ram": "2gb"
    },
    {
      "image":"samsung-galaxy-j1-sm-j100h1.jpg",
      "name": "Ios 7",
      "price": "100000",
      "camera": "25mp",
      "company": "iphone",
      "ram": "5gb"
    },
    {
      "image":"xiaomi-redmi-note-5-pro.jpg",
      "name": "Ios 2",
      "price": "110000",
      "camera": "20mp",
      "company": "iphone",
      "ram": "6gb"
    },
    {
      "image":"xiaomi-redmi-note-5-pro.jpg",
      "name": "meta 5",
      "price": "100000",
      "camera": "12mp",
      "company": "sony",
      "ram": "2gb"
    },
    {
      "image":"nokia-7-plus-.jpg",
      "name": "meta 5",
      "price": "100000",
      "camera": "12mp",
      "company": "sony",
      "ram": "2gb"
    },
    {
      "image":"samsung-galaxy-j1-sm-j100h1.jpg",
      "name": "galaxy a1",
      "price": "22000",
      "camera": "25mp",
      "company": "samsung",
      "ram": "2gb"
    },
    {
      "image":"nokia-7-plus-.jpg",
      "name": "galaxy a2",
      "price": "23000",
      "camera": "25mp",
      "company": "samsung",
      "ram": "2gb"
    },
    {
      "image":"nokia-7-plus-.jpg",
      "name": "galaxy a9",
      "price": "23000",
      "camera": "25mp",
      "company": "samsung",
      "ram": "2gb"
    }

  ]
}